{"Exif":{"Lat":43.82171,"Long":7.778856,"Date":"2019-12-11T18:41:45+01:00","Tags":{"ApertureValue":1.6993699982773005,"CreateDate":"2019:12:11 18:41:45","DateTimeOriginal":"2019:12:11 18:41:45","ExposureCompensation|*imagemeta.rat[int32]":"0","ExposureTime|*imagemeta.rat[int32]":"1/13","FNumber|*imagemeta.rat[uint32]":"17/10","FocalLengthIn35mmFormat|uint16":"25","FocalLength|*imagemeta.rat[uint32]":"17/4","ISO|uint16":"1000","ImageHeight|uint32":"3330","ImageUniqueID":"ef7d1d7dba1088b20000000000000000","ImageWidth|uint32":"3330","LightSource|uint32":"0","Make":"OnePlus","Model":"ONEPLUS A6003","ModifyDate":"2019:12:11 18:41:45","Orientation|uint16":"1","ShutterSpeedValue":0.08004749133311066,"Software":"Picasa","YCbCrSubSampling":[2,2]}}}
